{
  "yogaTypes": [
    {
      "source": "Example Source",
      "data": [
        {
          "name": "Hatha Yoga",
          "description": "Hatha yoga is a traditional form that emphasizes physical postures, breath control, and meditation.",
          "benefits": [
            "Improves strength and flexibility.",
            "Enhances mental clarity and focus.",
            "Reduces stress and promotes relaxation."
          ],
          "suitable_for": [
            "Beginners looking to learn the fundamentals.",
            "Those seeking a gentler, slower-paced practice."
          ]
        }
      ]
    }
  ],
  "poses": [
    {
      "source": "Example Source",
      "data": [
        {
          "name": "Downward-Facing Dog",
          "description": "An inversion pose that forms an inverted V-shape, stretching the entire back of the body.",
          "image_url": "https://example.com/downward-dog.jpg",
          "difficulty": "Beginner",
          "benefits": [
            "Strengthens the arms, shoulders, and legs.",
            "Stretches the hamstrings, calves, and spine.",
            "Energizes the body and calms the mind."
          ],
          "category": "inversions"
        }
      ]
    }
  ],
  "benefits": [
    {
      "source": "Example Source",
      "data": {
        "physical": [
          "Increases flexibility and muscle strength.",
          "Improves respiration, energy, and vitality.",
          "Maintains a balanced metabolism and promotes cardiovascular health."
        ],
        "mental": [
          "Reduces stress, anxiety, and depression.",
          "Improves focus, concentration, and mental clarity.",
          "Enhances mindfulness and body awareness."
        ],
        "general": [
          "Promotes better sleep patterns.",
          "Helps manage chronic conditions.",
          "Supports overall well-being."
        ]
      }
    }
  ],
  "tips": [
    {
      "source": "Example Source",
      "data": {
        "beginners": [
          "Start with beginner-friendly classes to learn proper alignment.",
          "Don't push beyond your comfort zone; listen to your body.",
          "Consistency is more important than intensity."
        ],
        "practice": [
          "Focus on your breath throughout your practice.",
          "Use modifications when needed to suit your body.",
          "Practice with intention, setting a purpose for each session."
        ],
        "props": [
          "Yoga blocks can help bring the floor closer in standing forward folds.",
          "Straps are useful for extending your reach in seated poses.",
          "Blankets provide support for seated meditation and joint comfort."
        ]
      }
    }
  ]
}
